fastabx/__init__.py
fastabx/__main__.py
fastabx/cell.py
fastabx/constraints.py
fastabx/dataset.py
fastabx/distance.py
fastabx/pooling.py
fastabx/py.typed
fastabx/score.py
fastabx/subsample.py
fastabx/task.py
fastabx/utils.py
fastabx/verify.py
fastabx/zerospeech.py
fastabx-0.7.0.dist-info/METADATA
fastabx-0.7.0.dist-info/WHEEL
fastabx-0.7.0.dist-info/entry_points.txt
fastabx-0.7.0.dist-info/licenses/LICENSE
fastabx-0.7.0.dist-info/RECORD
