Metadata-Version: 2.4
Name: fastabx
Version: 0.7.0
Summary: A library for efficient computation of ABX discriminability
Project-URL: changelog, https://github.com/bootphon/fastabx/releases
Project-URL: documentation, https://docs.cognitive-ml.fr/fastabx
Project-URL: homepage, https://docs.cognitive-ml.fr/fastabx
Project-URL: repository, https://github.com/bootphon/fastabx
Author: Maxime Poli
Author-email: CoML <dev@cognitive-ml.fr>
License-Expression: MIT
License-File: LICENSE
Keywords: machine learning,speech
Classifier: Development Status :: 4 - Beta
Classifier: Intended Audience :: Science/Research
Classifier: Operating System :: OS Independent
Classifier: Programming Language :: C++
Classifier: Programming Language :: Python :: 3 :: Only
Classifier: Programming Language :: Python :: 3.12
Classifier: Programming Language :: Python :: 3.13
Classifier: Topic :: Scientific/Engineering
Classifier: Topic :: Scientific/Engineering :: Artificial Intelligence
Requires-Python: >=3.12
Requires-Dist: numpy>=1.26.4
Requires-Dist: polars>=1.35.1
Requires-Dist: torch>=2.10.0
Requires-Dist: torchdtw>=0.1.0
Requires-Dist: tqdm>=4.67.1
